VideoService/__errors__.py
VideoService/__init__.py
VideoService/__main__.py
VideoService/database.py
VideoService/files_manager.py
VideoService/playlist.py
VideoService/video.py
VideoService-0.2.0.dist-info/LICENSE
VideoService-0.2.0.dist-info/METADATA
VideoService-0.2.0.dist-info/WHEEL
VideoService-0.2.0.dist-info/top_level.txt
VideoService-0.2.0.dist-info/RECORD
