Metadata-Version: 2.1
Name: VideoService
Version: 0.2.0
Summary: A library to create video services
Author: Dtar380
License: MIT License
Project-URL: homepage, https://github.com/Dtar380/VideoService
Project-URL: documentation, https://videoservice.readthedocs.io
Project-URL: repository, https://github.com/Dtar380/VideoService
Project-URL: Bug Tracker, https://github.com/Dtar380/VideoService/issues
Project-URL: changelog, https://github.com/Dtar380/VideoService/releases
Classifier: Development Status :: 4 - Beta
Classifier: Intended Audience :: Developers
Classifier: Topic :: Database :: Database Engines/Servers
Classifier: Topic :: Office/Business
Classifier: Topic :: Multimedia :: Video
Classifier: Operating System :: OS Independent
Classifier: License :: OSI Approved :: MIT License
Classifier: Programming Language :: Python :: 3
Classifier: Programming Language :: Python :: 3.8
Classifier: Programming Language :: Python :: 3.9
Classifier: Programming Language :: Python :: 3.10
Classifier: Programming Language :: Python :: 3.11
Classifier: Programming Language :: Python :: 3.12
Requires-Python: >=3.8
License-File: LICENSE
Requires-Dist: opencv-python==4.10.0.84
Provides-Extra: dev
Requires-Dist: build; extra == "dev"
Requires-Dist: twine; extra == "dev"
Requires-Dist: setuptools; extra == "dev"
Requires-Dist: wheel; extra == "dev"
Provides-Extra: test
Requires-Dist: pytest; extra == "test"
Requires-Dist: build; extra == "test"
Requires-Dist: twine; extra == "test"
Requires-Dist: setuptools; extra == "test"
Requires-Dist: wheel; extra == "test"
